UKFastAPI/__init__.py
UKFastAPI/base.py
UKFastAPI/config.py
UKFastAPI/exceptions.py
UKFastAPI/utils.py
UKFastAPI/SafeDNS/__init__.py
UKFastAPI/SafeDNS/config.py
UKFastAPI/SafeDNS/note.py
UKFastAPI/SafeDNS/record.py
UKFastAPI/SafeDNS/safedns.py
UKFastAPI/SafeDNS/settings.py
UKFastAPI/SafeDNS/template.py
UKFastAPI/SafeDNS/zone.py
UKFastAPI-0.0.2.data/data/VERSION
UKFastAPI-0.0.2.data/data/requirements.txt
UKFastAPI-0.0.2.data/data/setup.py
UKFastAPI-0.0.2.dist-info/METADATA
UKFastAPI-0.0.2.dist-info/WHEEL
UKFastAPI-0.0.2.dist-info/top_level.txt
UKFastAPI-0.0.2.dist-info/RECORD
